maxmind_api/__init__.py
maxmind_api-0.2.dist-info/DESCRIPTION.rst
maxmind_api-0.2.dist-info/METADATA
maxmind_api-0.2.dist-info/RECORD
maxmind_api-0.2.dist-info/WHEEL
maxmind_api-0.2.dist-info/metadata.json
maxmind_api-0.2.dist-info/top_level.txt
