Metadata-Version: 2.0
Name: maxmind-api
Version: 0.2
Summary: UNKNOWN
Home-page: https://volsor.com/
Author: Volsor
Author-email: admin@volsor.com
License: Proprietary
Platform: UNKNOWN
Classifier: Development Status :: 2 - Pre-Alpha
Classifier: Environment :: Console
Classifier: Intended Audience :: Developers
Classifier: Operating System :: OS Independent
Classifier: Programming Language :: Python
Classifier: Programming Language :: Python :: 2.7
Classifier: Programming Language :: Python :: 3.4
Classifier: Programming Language :: Python :: 3.5
Classifier: Programming Language :: Python :: Implementation :: CPython
Requires-Dist: requests
